slsdet/PatternGenerator.py
slsdet/VERSION
slsdet/__init__.py
slsdet/_slsdet.cpython-312-x86_64-linux-gnu.so
slsdet/adcs.py
slsdet/bits.py
slsdet/ctb.py
slsdet/dacs.py
slsdet/decorators.py
slsdet/defines.py
slsdet/detector.py
slsdet/detector_property.py
slsdet/eiger.py
slsdet/enums.py
slsdet/errors.py
slsdet/gaincaps.py
slsdet/gotthard2.py
slsdet/jungfrau.py
slsdet/lookup.py
slsdet/moench.py
slsdet/mythen3.py
slsdet/pattern.py
slsdet/powers.py
slsdet/proxy.py
slsdet/registers.py
slsdet/temperature.py
slsdet/utils.py
slsdet-10.0.0.dist-info/METADATA
slsdet-10.0.0.dist-info/WHEEL
slsdet-10.0.0.dist-info/RECORD
slsdet-10.0.0.dist-info/licenses/COPYING
