Metadata-Version: 2.2
Name: slsdet
Version: 10.0.0
Requires-Dist: numpy
